annotation_gpt/__init__.py
annotation_gpt/annotation/__init__.py
annotation_gpt/annotation/object.py
annotation_gpt/annotation/summarization/__init__.py
annotation_gpt/annotation/summarization/abc.py
annotation_gpt/annotation/summarization/openai.py
annotation_gpt/config.py
annotation_gpt/schema/__init__.py
annotation_gpt/schema/chat.py
annotation_gpt/schema/openai/__init__.py
annotation_gpt/schema/openai/result.py
annotation_gpt/schema/result.py
annotation_gpt/util/__init__.py
annotation_gpt/util/openai/__init__.py
annotation_gpt/util/openai/credential.py
annotation_gpt/version.py
annotation_gpt-0.1.0.dist-info/LICENSE
annotation_gpt-0.1.0.dist-info/METADATA
annotation_gpt-0.1.0.dist-info/WHEEL
annotation_gpt-0.1.0.dist-info/RECORD
